sorn/__init__.py
sorn/callbacks.py
sorn/sorn.py
sorn/utils.py
sorn-0.7.4.data/data/LICENSE.md
sorn-0.7.4.dist-info/LICENSE.md
sorn-0.7.4.dist-info/METADATA
sorn-0.7.4.dist-info/WHEEL
sorn-0.7.4.dist-info/top_level.txt
sorn-0.7.4.dist-info/RECORD
