Metadata-Version: 2.1
Name: sorn
Version: 0.7.4
Summary: Self-Organizing Recurrent Neural Networks
Home-page: https://github.com/Saran-nns/sorn
Author: Saranraj Nambusubramaniyan
Author-email: saran_nns@hotmail.com
License: OSI Approved :: MIT License
Keywords: Brain-Inspired Computing,Artificial Neural Networks,Neuro Informatics,Spiking Cortical Networks,Neural Connectomics,Neuroscience,Artificial General Intelligence,Neural Information Processing
Platform: UNKNOWN
Classifier: Development Status :: 3 - Alpha
Classifier: Topic :: Scientific/Engineering :: Artificial Intelligence
Classifier: License :: OSI Approved :: MIT License
Classifier: Programming Language :: Python :: 3
Classifier: Programming Language :: Python :: 3.7
Classifier: Programming Language :: Python :: 3.8
Classifier: Programming Language :: Python :: 3.9
License-File: LICENSE.md
Requires-Dist: numpy
Requires-Dist: configparser
Requires-Dist: scipy
Requires-Dist: seaborn
Requires-Dist: pandas
Requires-Dist: networkx
